shortbus/__init__.py
shortbus/components.py
shortbus/transpiler.py
shortbus-0.1.0.dist-info/DESCRIPTION.rst
shortbus-0.1.0.dist-info/METADATA
shortbus-0.1.0.dist-info/RECORD
shortbus-0.1.0.dist-info/WHEEL
shortbus-0.1.0.dist-info/metadata.json
shortbus-0.1.0.dist-info/top_level.txt
