Metadata-Version: 2.0
Name: shortbus
Version: 0.1.0
Summary: Tools to convert Sublime Text snippets into Jetbrains live templates and vice versa
Home-page: https://github.com/brmc/shortbus
Author: Brian McClure
Author-email: brian@mcclure.pw
License: MIT license
Keywords: shortbus
Platform: UNKNOWN
Classifier: Development Status :: 2 - Pre-Alpha
Classifier: Intended Audience :: Developers
Classifier: License :: OSI Approved :: MIT License
Classifier: Natural Language :: English
Classifier: Programming Language :: Python :: 3.6
Requires-Dist: lxml
Requires-Dist: pyyaml
